BlackSwanlab/__init__.py
BlackSwanlab/server.py
BlackSwanlab/tracker.py
MLSwanlab/__init__.py
MLSwanlab/server.py
MLSwanlab/tracker.py
MLSwanlab-0.0.1.dist-info/LICENSE
MLSwanlab-0.0.1.dist-info/METADATA
MLSwanlab-0.0.1.dist-info/WHEEL
MLSwanlab-0.0.1.dist-info/top_level.txt
MLSwanlab-0.0.1.dist-info/RECORD
