Metadata-Version: 2.1
Name: MLSwanlab
Version: 0.0.1
Summary: A python package which can help you visually track your training process of machine-learning
Home-page: https://swanlab.co
Author: MLSwanlab
Author-email: MLSwanlab <22009100671@stu.xidian.edu.cn>
Project-URL: Homepage, https://github.com/Blackswan-lab/BlackSwanlab
Project-URL: Bug Tracker, https://github.com/Blackswan-lab/BlackSwanlab/issues
Classifier: Programming Language :: Python :: 3
Classifier: License :: OSI Approved :: MIT License
Classifier: Operating System :: OS Independent
Requires-Python: >=3.7
License-File: LICENSE
Requires-Dist: flask
Requires-Dist: torch
Requires-Dist: numpy
Requires-Dist: time
Requires-Dist: random
Requires-Dist: threading
